st_quill_dark_mode/__init__.py
st_quill_dark_mode/frontend/build/asset-manifest.json
st_quill_dark_mode/frontend/build/bootstrap.min.css
st_quill_dark_mode/frontend/build/index.html
st_quill_dark_mode/frontend/build/precache-manifest.518a49ab850502cb99c2664eda65b59a.js
st_quill_dark_mode/frontend/build/service-worker.js
st_quill_dark_mode/frontend/build/static/css/main.ad6d5a17.chunk.css
st_quill_dark_mode/frontend/build/static/css/main.ad6d5a17.chunk.css.map
st_quill_dark_mode/frontend/build/static/js/2.ecf90cd3.chunk.js
st_quill_dark_mode/frontend/build/static/js/2.ecf90cd3.chunk.js.LICENSE.txt
st_quill_dark_mode/frontend/build/static/js/2.ecf90cd3.chunk.js.map
st_quill_dark_mode/frontend/build/static/js/main.c9752ecc.chunk.js
st_quill_dark_mode/frontend/build/static/js/main.c9752ecc.chunk.js.map
st_quill_dark_mode/frontend/build/static/js/runtime-main.44d30fc2.js
st_quill_dark_mode/frontend/build/static/js/runtime-main.44d30fc2.js.map
st_quill_dark_mode-0.0.3.dist-info/LICENSE
st_quill_dark_mode-0.0.3.dist-info/METADATA
st_quill_dark_mode-0.0.3.dist-info/WHEEL
st_quill_dark_mode-0.0.3.dist-info/top_level.txt
st_quill_dark_mode-0.0.3.dist-info/RECORD
