Metadata-Version: 2.1
Name: st-quill-dark-mode
Version: 0.0.3
Summary: Dark Streamlit Quill Editor.
Home-page: 
Author: Bryan Saggese
Author-email: 
Requires-Python: >=3.6
License-File: LICENSE
Requires-Dist: streamlit (>=0.63)
